{
    "campaign_id": "BDC-2026-001",
    "operation": "Operation Black Eclipse",
    "campaign_phase": "Containment",
    "total_cases": 3,
    "active_cases": 64,
    "closed_cases": 0,
    "low_cases": 0,
    "moderate_cases": 2,
    "high_cases": 0,
    "critical_cases": 1,
    "affected_facilities": 7,
    "affected_states": 3,
    "evidence_items": 423,
    "digital_artifacts": 110,
    "ioc_count": 328,
    "containment_level": "SEVERE",
    "confidence": 96,
    "last_updated": "2026-07-16"
}